get_wayback_machine/__init__.py
get_wayback_machine/get.py
get_wayback_machine-0.1.2.dist-info/LICENSE
get_wayback_machine-0.1.2.dist-info/METADATA
get_wayback_machine-0.1.2.dist-info/WHEEL
get_wayback_machine-0.1.2.dist-info/top_level.txt
get_wayback_machine-0.1.2.dist-info/RECORD
