Metadata-Version: 2.1
Name: get-wayback-machine
Version: 0.1.2
Summary: Fetch a URL via the latest Wayback Machine Snapshot
Home-page: https://github.com/jfilter/get-wayback-machine
Author: Johannes Filter
Author-email: hi@jfilter.de
License: MIT
Platform: UNKNOWN
Classifier: Programming Language :: Python :: 3.6
Classifier: Programming Language :: Python :: 3.7
Classifier: License :: OSI Approved :: MIT License
Requires-Dist: get-retries
